coolamqp/__init__.py
coolamqp/argumentify.py
coolamqp/exceptions.py
coolamqp/objects.py
coolamqp/tracing.py
coolamqp/utils.py
coolamqp/attaches/__init__.py
coolamqp/attaches/agroup.py
coolamqp/attaches/channeler.py
coolamqp/attaches/consumer.py
coolamqp/attaches/declarer.py
coolamqp/attaches/publisher.py
coolamqp/attaches/utils.py
coolamqp/clustering/__init__.py
coolamqp/clustering/cluster.py
coolamqp/clustering/events.py
coolamqp/clustering/single.py
coolamqp/framing/__init__.py
coolamqp/framing/base.py
coolamqp/framing/definitions.py
coolamqp/framing/field_table.py
coolamqp/framing/frames.py
coolamqp/framing/compilation/__init__.py
coolamqp/framing/compilation/content_property.py
coolamqp/framing/compilation/textcode_fields.py
coolamqp/framing/compilation/utilities.py
coolamqp/uplink/__init__.py
coolamqp/uplink/handshake.py
coolamqp/uplink/heartbeat.py
coolamqp/uplink/connection/__init__.py
coolamqp/uplink/connection/connection.py
coolamqp/uplink/connection/recv_framer.py
coolamqp/uplink/connection/send_framer.py
coolamqp/uplink/connection/states.py
coolamqp/uplink/connection/watches.py
coolamqp/uplink/listener/__init__.py
coolamqp/uplink/listener/base_listener.py
coolamqp/uplink/listener/epoll_listener.py
coolamqp/uplink/listener/select_listener.py
coolamqp/uplink/listener/socket.py
coolamqp/uplink/listener/thread.py
CoolAMQP-2.1.2.dist-info/LICENSE.md
CoolAMQP-2.1.2.dist-info/METADATA
CoolAMQP-2.1.2.dist-info/WHEEL
CoolAMQP-2.1.2.dist-info/top_level.txt
CoolAMQP-2.1.2.dist-info/RECORD
