Metadata-Version: 2.1
Name: CoolAMQP
Version: 2.1.2
Summary: Very fast pure-Python AMQP client
Home-page: https://git.dms-serwis.com.pl/smokserwis/coolamqp
Author: Piotr Maślanka
Author-email: pmaslanka@smok.co
License: MIT License
Keywords: amqp,rabbitmq,client,network,ha,high availability
Platform: posix
Platform: win32
Classifier: Programming Language :: Python
Classifier: Programming Language :: Python :: 2.7
Classifier: Programming Language :: Python :: 3.5
Classifier: Programming Language :: Python :: 3.6
Classifier: Programming Language :: Python :: 3.7
Classifier: Programming Language :: Python :: 3.8
Classifier: Programming Language :: Python :: 3.9
Classifier: Programming Language :: Python :: 3.10
Classifier: Programming Language :: Python :: 3.11
Classifier: Programming Language :: Python :: Implementation :: CPython
Classifier: Programming Language :: Python :: Implementation :: PyPy
Classifier: Operating System :: OS Independent
Classifier: Development Status :: 5 - Production/Stable
Classifier: License :: OSI Approved :: MIT License
Classifier: Topic :: Software Development :: Libraries
Classifier: Intended Audience :: Developers
Classifier: Topic :: Software Development :: Libraries :: Python Modules
Requires-Python: !=3.0.*,!=3.1.*,!=3.2.*,!=3.3.*,!=3.4.*
License-File: LICENSE.md
Requires-Dist: six
Requires-Dist: futures; python_version == "2.7"
Requires-Dist: typing; python_version == "2.7"
Requires-Dist: monotonic; python_version == "2.7"
Provides-Extra: gevent
Requires-Dist: gevent; extra == "gevent"
Provides-Extra: opentracing
Requires-Dist: opentracing; extra == "opentracing"
Provides-Extra: setproctitle
Requires-Dist: setproctitle; extra == "setproctitle"
